changesets/__init__.py
changesets/py.typed
changesets-0.4.1.dist-info/METADATA
changesets-0.4.1.dist-info/WHEEL
changesets-0.4.1.dist-info/entry_points.txt
changesets-0.4.1.dist-info/RECORD
